[
  {
    "numeroCarteBancaire": "4974 0185 0223 4197",
    "Montant": -2901.98,
    "Type": 0,
    "Date": "2025-03-12T17:07:37.6987813+01:00",
    "Devise": "CAD",
    "TauxConversion": 1.58
  },
  {
    "numeroCarteBancaire": "4974 0185 0223 4053",
    "Montant": -4639.34,
    "Type": 2,
    "Date": "2025-03-12T17:07:38.6975856+01:00",
    "Devise": "EUR",
    "TauxConversion": 1
  },
  {
    "numeroCarteBancaire": "4974 0185 0223 6249",
    "Montant": -2238.52,
    "Type": 2,
    "Date": "2025-03-12T17:07:39.1797019+01:00",
    "Devise": "EUR",
    "TauxConversion": 1
  },
  {
    "numeroCarteBancaire": "4974 0185 0223 4197",
    "Montant": -106.34,
    "Type": 0,
    "Date": "2025-03-12T17:07:39.634723+01:00",
    "Devise": "???",
    "TauxConversion": -1
  },
  {
    "numeroCarteBancaire": "4974 0185 0223 4104",
    "Montant": -4523.29,
    "Type": 0,
    "Date": "2025-03-12T17:07:40.0855991+01:00",
    "Devise": "JPY",
    "TauxConversion": 161.21
  },
  {
    "numeroCarteBancaire": "4974 0185 0223 4555",
    "Montant": -7105.37,
    "Type": 0,
    "Date": "2025-03-12T17:07:40.5439595+01:00",
    "Devise": "???",
    "TauxConversion": -1
  },
  {
    "numeroCarteBancaire": "4974 0185 0223 4088",
    "Montant": -259.14,
    "Type": 2,
    "Date": "2025-03-12T17:07:40.9974072+01:00",
    "Devise": "EUR",
    "TauxConversion": 1
  },
  {
    "numeroCarteBancaire": "4974 0185 0223 4120",
    "Montant": 8840.57,
    "Type": 1,
    "Date": "2025-03-12T17:07:41.4558045+01:00",
    "Devise": "???",
    "TauxConversion": -1
  },
  {
    "numeroCarteBancaire": "4974 0185 0223 4096",
    "Montant": 2147.54,
    "Type": 1,
    "Date": "2025-03-12T17:07:41.9095007+01:00",
    "Devise": "USD",
    "TauxConversion": 1.09
  },
  {
    "numeroCarteBancaire": "4974 0185 0223 4104",
    "Montant": -2319.16,
    "Type": 2,
    "Date": "2025-03-12T17:07:42.3791041+01:00",
    "Devise": "JPY",
    "TauxConversion": 161.21
  }
]